LICENSE
MANIFEST.in
README.md
setup.cfg
setup.py
som/__init__.py
som/dicom.py
som/logger.py
som/utils.py
som/version.py
som.egg-info/PKG-INFO
som.egg-info/SOURCES.txt
som.egg-info/dependency_links.txt
som.egg-info/entry_points.txt
som.egg-info/requires.txt
som.egg-info/top_level.txt
som/api/__init__.py
som/api/base/README.md
som/api/base/__init__.py
som/api/base/auth.py
som/api/google/__init__.py
som/api/google/dlp/__init__.py
som/api/google/dlp/client.py
som/api/google/dlp/utils.py
som/api/google/storage/README.md
som/api/google/storage/__init__.py
som/api/google/storage/bigquery.py
som/api/google/storage/client.py
som/api/google/storage/datastore.py
som/api/google/storage/general.py
som/api/google/storage/models.py
som/api/google/storage/utils.py
som/api/google/storage/validators.py
som/api/identifiers/__init__.py
som/api/identifiers/client.py
som/api/identifiers/standards.py
som/api/identifiers/utils.py
som/api/identifiers/data/__init__.py
som/api/identifiers/data/developers_uid.json
som/api/identifiers/dicom/README.md
som/api/identifiers/dicom/__init__.py
som/api/identifiers/dicom/settings.py
som/api/identifiers/dicom/tasks.py
som/api/identifiers/dicom/utils.py
som/api/identifiers/validators/__init__.py
som/api/identifiers/validators/requests.py
som/api/identifiers/validators/responses.py
som/api/identifiers/validators/utils.py
som/cli/__init__.py
som/cli/get.py
som/cli/requester.py
som/cli/search.py
som/cli/static/css/codemirror.css
som/cli/static/css/dataset_explorer.css
som/cli/static/css/jscolors.css
som/cli/static/css/mdn-like.css
som/cli/static/js/codemirror.js
som/cli/static/js/dataset_explorer.js
som/cli/static/js/editor.js
som/cli/static/js/parsejavascript.js
som/cli/static/js/select.js
som/cli/static/js/sketch.js
som/cli/static/js/stringstream.js
som/cli/static/js/tokenize.js
som/cli/static/js/tokenizejavascript.js
som/cli/static/js/undo.js
som/cli/static/js/util.js
som/logger/__init__.py
som/logger/message.py
som/logger/progress.py
som/logger/spinner.py
som/wordfish/__init__.py
som/wordfish/base.py
som/wordfish/cli.py
som/wordfish/structures.py
som/wordfish/validators.py