Metadata-Version: 1.1
Name: som
Version: 0.2.3
Summary: stanford open modules for python
Home-page: https://github.com/vsoch/som
Author: Vanessa Sochat
Author-email: vsochat@stanford.edu
License: LICENSE
Keywords: open source,stanford,python,google,gce,storage,api,validator
Platform: UNKNOWN
Classifier: Development Status :: 5 - Production/Stable
Classifier: Environment :: Console
Classifier: Intended Audience :: Developers
Classifier: Intended Audience :: System Administrators
Classifier: Intended Audience :: Science/Research
Classifier: License :: OSI Approved :: MIT License
Classifier: Natural Language :: English
Classifier: Operating System :: Unix
Classifier: Programming Language :: Python
Classifier: Programming Language :: Python :: 3
Classifier: Programming Language :: Python :: 3.2
Classifier: Programming Language :: Python :: 3.3
Classifier: Programming Language :: Python :: 3.4
Classifier: Programming Language :: Python :: 3.5
Classifier: Topic :: Software Development
Classifier: Topic :: Scientific/Engineering
Classifier: Topic :: System :: Shells
Classifier: Topic :: Terminals
Classifier: Topic :: Utilities
